{
  "prefix": "Conflict & Negative Concepts",
  "affixType": "topic",
  "meanings": [
    {
      "meaningId": "topic_conflict_negation",
      "displayName": "冲突与负面概念 (Conflict & Negative Concepts)",
      "themeColor": "#ef4444",
      "prefixVisual": "<path d='M12 2L2 22H22L12 2Z M11 10H13V16H11V10Z M11 18H13V20H11V18Z' fill='none'/>",
      "prefixIntro": {
        "title": "冲突与负面概念",
        "description": "包含表示冲突、禁止、危机、错误、负面情绪以及不良行为的词汇。",
        "imagery": "一个红色的警告标志，或者断裂的链条，警示着危险和错误的发生。"
      },
      "words": [
        {
          "word": "weak",
          "rootVisual": "<path d='M6 18h12' stroke='currentColor' stroke-width='2'/><path d='M12 18v-8' stroke='currentColor' stroke-dasharray='2 2'/><circle cx='12' cy='8' r='2' stroke='currentColor' fill='none'/>",
          "breakdown": [
            "weak"
          ],
          "imagery": "一根弯曲、快要折断的树枝，或者一个举不起哑铃的人。",
          "translation": "虚弱的",
          "sentences": [
            {
              "en": "He's not so weak as he looks.",
              "cn": "他不像他看起来那么虚弱。"
            }
          ]
        },
        {
          "word": "upset",
          "rootVisual": "<circle cx='12' cy='12' r='8' stroke='currentColor' fill='none'/><path d='M8 10h2 M14 10h2' stroke='currentColor'/><path d='M8 16c2-2 6-2 8 0' stroke='currentColor'/>",
          "breakdown": [
            "up",
            "set"
          ],
          "imagery": "一个翻倒的水杯，水洒了一地。",
          "translation": "不安的；心烦的",
          "sentences": [
            {
              "en": "What makes you so upset?",
              "cn": "是什么让你如此心烦？"
            }
          ]
        },
        {
          "word": "mad",
          "rootVisual": "<circle cx='12' cy='12' r='8' stroke='currentColor' fill='none'/><path d='M8 9l2 2 M14 11l2-2' stroke='currentColor' stroke-width='2'/><path d='M8 16c2-2 6-2 8 0' stroke='currentColor'/>",
          "breakdown": [
            "mad"
          ],
          "imagery": "一个冒着气的愤怒表情符号。",
          "translation": "生气的；疯狂的",
          "sentences": [
            {
              "en": "You make me so mad.",
              "cn": "你快把我气疯了。"
            }
          ]
        },
        {
          "word": "down",
          "rootVisual": "<circle cx='12' cy='12' r='8' stroke='currentColor' fill='none'/><path d='M8 10h2 M14 10h2' stroke='currentColor'/><path d='M8 16c2-1 6-1 8 0' stroke='currentColor'/>",
          "breakdown": [
            "down"
          ],
          "imagery": "一个垂头丧气的人，或者向下的箭头。",
          "translation": "悲伤的；沮丧的",
          "sentences": [
            {
              "en": "I felt down.",
              "cn": "我感觉很难过。"
            }
          ]
        },
        {
          "word": "cruel",
          "rootVisual": "<path d='M12 2l3 9h9l-7 5 3 9-8-6-8 6 3-9-7-5h9z' stroke='currentColor' fill='none'/><path d='M4 4l16 16' stroke='currentColor' stroke-width='2' stroke='red'/>",
          "breakdown": [
            "cruel"
          ],
          "imagery": "一个带刺的鞭子，或者一只凶恶的野兽。",
          "translation": "残酷的；残忍的",
          "sentences": [
            {
              "en": "He is cruel to animals.",
              "cn": "他对动物很残忍。"
            }
          ]
        },
        {
          "word": "foolish",
          "rootVisual": "<circle cx='12' cy='12' r='8' stroke='currentColor' fill='none'/><circle cx='8' cy='10' r='1' fill='currentColor'/><circle cx='16' cy='10' r='1' fill='currentColor'/><path d='M12 14v4' stroke='currentColor'/><path d='M10 18h4' stroke='currentColor'/>",
          "breakdown": [
            "fool",
            "-ish"
          ],
          "imagery": "一个人戴着驴耳朵帽子。",
          "translation": "愚蠢的",
          "sentences": [
            {
              "en": "It was a foolish mistake.",
              "cn": "那是个愚蠢的错误。"
            }
          ]
        },
        {
          "word": "waste",
          "rootVisual": "<path d='M6 6l12 12 M18 6l-12 12' stroke='currentColor' stroke-width='2'/><rect x='8' y='20' width='8' height='4' fill='currentColor'/>",
          "breakdown": [
            "waste"
          ],
          "imagery": "一个漏水的水龙头，或者扔进垃圾桶的食物。",
          "translation": "浪费",
          "sentences": [
            {
              "en": "It's a waste of time.",
              "cn": "这是浪费时间。"
            }
          ]
        },
        {
          "word": "fail",
          "rootVisual": "<text x='6' y='18' font-size='20' fill='red' font-weight='bold'>F</text>",
          "breakdown": [
            "fail"
          ],
          "imagery": "试卷上大大的红色F，或者跌倒的小人。",
          "translation": "失败；不及格",
          "sentences": [
            {
              "en": "He failed math.",
              "cn": "他数学不及格。"
            }
          ]
        },
        {
          "word": "punish",
          "rootVisual": "<rect x='4' y='4' width='16' height='16' stroke='currentColor' fill='none'/><path d='M4 4l16 16 M20 4l-16 16' stroke='currentColor'/>",
          "breakdown": [
            "pun (罚)",
            "-ish"
          ],
          "imagery": "一把戒尺，或者关禁闭的房间。",
          "translation": "惩罚",
          "sentences": [
            {
              "en": "They were punished by the teacher.",
              "cn": "他们被老师惩罚了。"
            }
          ]
        },
        {
          "word": "warn",
          "rootVisual": "<path d='M12 2L2 22h20L12 2z' stroke='currentColor' fill='yellow'/><path d='M12 8v8 M12 18v2' stroke='black' stroke-width='2'/>",
          "breakdown": [
            "warn"
          ],
          "imagery": "一个黄色的三角形警告标志，中间有感叹号。",
          "translation": "警告",
          "sentences": [
            {
              "en": "I warned you.",
              "cn": "我警告过你。"
            }
          ]
        },
        {
          "word": "steal",
          "rootVisual": "<path d='M8 12h8' stroke='currentColor'/><path d='M12 8v8' stroke='currentColor' stroke-dasharray='2 2'/><rect x='10' y='10' width='4' height='4' fill='black'/>",
          "breakdown": [
            "steal"
          ],
          "imagery": "一只手悄悄伸向钱包。",
          "translation": "偷",
          "sentences": [
            {
              "en": "He stole money.",
              "cn": "他偷了钱。"
            }
          ]
        },
        {
          "word": "hoax",
          "rootVisual": "<rect x='4' y='6' width='16' height='12' stroke='currentColor' fill='none'/><text x='6' y='14' font-size='8' fill='currentColor'>FAKE</text>",
          "breakdown": [
            "hoax"
          ],
          "imagery": "一个假面具，或者一条假新闻。",
          "translation": "恶作剧；骗局",
          "sentences": [
            {
              "en": "It is just a hoax.",
              "cn": "这只是个恶作剧。"
            }
          ]
        },
        {
          "word": "litter",
          "rootVisual": "<path d='M4 20h16' stroke='currentColor'/><circle cx='8' cy='18' r='1' fill='currentColor'/><rect x='12' y='18' width='2' height='2' fill='currentColor'/><path d='M16 16l2 2' stroke='currentColor'/>",
          "breakdown": [
            "litter"
          ],
          "imagery": "草地上散落的纸团和瓶子。",
          "translation": "乱扔垃圾",
          "sentences": [
            {
              "en": "Don't litter.",
              "cn": "不要乱扔垃圾。"
            }
          ]
        },
        {
          "word": "war",
          "rootVisual": "<path d='M4 18l4-10 4 6 4-10 4 14' stroke='currentColor' fill='none'/><circle cx='12' cy='4' r='2' fill='red' opacity='0.5'/>",
          "breakdown": [
            "war"
          ],
          "imagery": "交叉的剑，或者爆炸的蘑菇云。",
          "translation": "战争",
          "sentences": [
            {
              "en": "How many people died in the war?",
              "cn": "有多少人在战争中死亡？"
            }
          ]
        },
        {
          "word": "avoid",
          "rootVisual": "<path d='M4 12h6l2-4 2 8 2-4h4' stroke='currentColor' fill='none'/><circle cx='12' cy='12' r='8' stroke='currentColor' fill='none' opacity='0.3'/>",
          "breakdown": [
            "a-",
            "void"
          ],
          "imagery": "一个行人绕开地上的水坑。",
          "translation": "避免",
          "sentences": [
            {
              "en": "How can you avoid this?",
              "cn": "你如何能避免这件事？"
            }
          ]
        }
      ]
    }
  ]
}
